airflow_pentaho/__init__.py
airflow_pentaho/plugin.py
airflow_pentaho/hooks/__init__.py
airflow_pentaho/hooks/carte.py
airflow_pentaho/hooks/kettle.py
airflow_pentaho/operators/CarteJobOperator.py
airflow_pentaho/operators/CarteTransOperator.py
airflow_pentaho/operators/KitchenOperator.py
airflow_pentaho/operators/PanOperator.py
airflow_pentaho/operators/__init__.py
airflow_pentaho/operators/carte.py
airflow_pentaho/operators/kettle.py
airflow_pentaho_plugin-1.2.3.dist-info/LICENSE.txt
airflow_pentaho_plugin-1.2.3.dist-info/METADATA
airflow_pentaho_plugin-1.2.3.dist-info/WHEEL
airflow_pentaho_plugin-1.2.3.dist-info/entry_points.txt
airflow_pentaho_plugin-1.2.3.dist-info/top_level.txt
airflow_pentaho_plugin-1.2.3.dist-info/RECORD
